{
  "annotations": {
    "list": [
      {
        "builtIn": 1,
        "datasource": {
          "type": "grafana",
          "uid": "-- Grafana --"
        },
        "enable": true,
        "hide": true,
        "iconColor": "rgba(0, 211, 255, 1)",
        "name": "Annotations & Alerts",
        "type": "dashboard"
      }
    ]
  },
  "editable": true,
  "fiscalYearStartMonth": 0,
  "graphTooltip": 0,
  "id": null,
  "links": [],
  "liveNow": false,
  "panels": [
    {
      "datasource": {
        "type": "loki",
        "uid": "loki"
      },
      "fieldConfig": {
        "defaults": {
          "color": {
            "mode": "palette-classic"
          },
          "custom": {
            "axisCenteredZero": false,
            "axisColorMode": "text",
            "axisLabel": "Requests/sec",
            "axisPlacement": "auto",
            "barAlignment": 0,
            "drawStyle": "line",
            "fillOpacity": 20,
            "gradientMode": "none",
            "hideFrom": {
              "tooltip": false,
              "viz": false,
              "legend": false
            },
            "lineInterpolation": "linear",
            "lineWidth": 2,
            "pointSize": 5,
            "scaleDistribution": {
              "type": "linear"
            },
            "showPoints": "never",
            "spanNulls": false,
            "stacking": {
              "group": "A",
              "mode": "none"
            },
            "thresholdsStyle": {
              "mode": "off"
            }
          },
          "mappings": [],
          "thresholds": {
            "mode": "absolute",
            "steps": [
              {
                "color": "green",
                "value": null
              }
            ]
          },
          "unit": "reqps"
        },
        "overrides": []
      },
      "gridPos": {
        "h": 8,
        "w": 12,
        "x": 0,
        "y": 0
      },
      "id": 1,
      "options": {
        "legend": {
          "calcs": ["mean", "max"],
          "displayMode": "table",
          "placement": "bottom",
          "showLegend": true
        },
        "tooltip": {
          "mode": "multi",
          "sort": "none"
        }
      },
      "targets": [
        {
          "datasource": {
            "type": "loki",
            "uid": "loki"
          },
          "expr": "sum(rate({app=\"ts-waf-demo\", logger=\"gunicorn.access\"}[$__interval])) by (method)",
          "refId": "A",
          "legendFormat": "{{method}}"
        }
      ],
      "title": "Request Rate by Method",
      "type": "timeseries"
    },
    {
      "datasource": {
        "type": "loki",
        "uid": "loki"
      },
      "fieldConfig": {
        "defaults": {
          "color": {
            "mode": "thresholds"
          },
          "mappings": [],
          "thresholds": {
            "mode": "absolute",
            "steps": [
              {
                "color": "green",
                "value": null
              },
              {
                "color": "yellow",
                "value": 100
              },
              {
                "color": "red",
                "value": 500
              }
            ]
          },
          "unit": "ms"
        },
        "overrides": []
      },
      "gridPos": {
        "h": 8,
        "w": 12,
        "x": 12,
        "y": 0
      },
      "id": 2,
      "options": {
        "orientation": "auto",
        "reduceOptions": {
          "values": false,
          "calcs": ["lastNotNull"],
          "fields": ""
        },
        "showThresholdLabels": false,
        "showThresholdMarkers": true
      },
      "pluginVersion": "10.0.0",
      "targets": [
        {
          "datasource": {
            "type": "loki",
            "uid": "loki"
          },
          "expr": "quantile_over_time(0.50, {app=\"ts-waf-demo\", logger=\"gunicorn.access\"} | json | unwrap latency_ms [$__interval]) by ()",
          "refId": "A",
          "legendFormat": "p50"
        },
        {
          "datasource": {
            "type": "loki",
            "uid": "loki"
          },
          "expr": "quantile_over_time(0.95, {app=\"ts-waf-demo\", logger=\"gunicorn.access\"} | json | unwrap latency_ms [$__interval]) by ()",
          "refId": "B",
          "legendFormat": "p95"
        },
        {
          "datasource": {
            "type": "loki",
            "uid": "loki"
          },
          "expr": "quantile_over_time(0.99, {app=\"ts-waf-demo\", logger=\"gunicorn.access\"} | json | unwrap latency_ms [$__interval]) by ()",
          "refId": "C",
          "legendFormat": "p99"
        }
      ],
      "title": "Response Time Percentiles",
      "type": "gauge"
    },
    {
      "datasource": {
        "type": "loki",
        "uid": "loki"
      },
      "fieldConfig": {
        "defaults": {
          "color": {
            "mode": "palette-classic"
          },
          "custom": {
            "hideFrom": {
              "tooltip": false,
              "viz": false,
              "legend": false
            }
          },
          "mappings": []
        },
        "overrides": [
          {
            "matcher": {
              "id": "byName",
              "options": "200"
            },
            "properties": [
              {
                "id": "color",
                "value": {
                  "fixedColor": "green",
                  "mode": "fixed"
                }
              }
            ]
          },
          {
            "matcher": {
              "id": "byName",
              "options": "403"
            },
            "properties": [
              {
                "id": "color",
                "value": {
                  "fixedColor": "orange",
                  "mode": "fixed"
                }
              }
            ]
          },
          {
            "matcher": {
              "id": "byRegexp",
              "options": "^5.*"
            },
            "properties": [
              {
                "id": "color",
                "value": {
                  "fixedColor": "red",
                  "mode": "fixed"
                }
              }
            ]
          }
        ]
      },
      "gridPos": {
        "h": 8,
        "w": 12,
        "x": 0,
        "y": 8
      },
      "id": 3,
      "options": {
        "legend": {
          "displayMode": "table",
          "placement": "right",
          "showLegend": true,
          "values": ["value", "percent"]
        },
        "pieType": "donut",
        "tooltip": {
          "mode": "single",
          "sort": "none"
        }
      },
      "targets": [
        {
          "datasource": {
            "type": "loki",
            "uid": "loki"
          },
          "expr": "sum(count_over_time({app=\"ts-waf-demo\", logger=\"gunicorn.access\"}[$__interval])) by (status)",
          "refId": "A",
          "legendFormat": "{{status}}"
        }
      ],
      "title": "Status Code Distribution",
      "type": "piechart"
    },
    {
      "datasource": {
        "type": "loki",
        "uid": "loki"
      },
      "fieldConfig": {
        "defaults": {
          "color": {
            "mode": "palette-classic"
          },
          "custom": {
            "axisCenteredZero": false,
            "axisColorMode": "text",
            "axisLabel": "",
            "axisPlacement": "auto",
            "barAlignment": 0,
            "drawStyle": "line",
            "fillOpacity": 10,
            "gradientMode": "none",
            "hideFrom": {
              "tooltip": false,
              "viz": false,
              "legend": false
            },
            "lineInterpolation": "linear",
            "lineWidth": 1,
            "pointSize": 5,
            "scaleDistribution": {
              "type": "linear"
            },
            "showPoints": "never",
            "spanNulls": false,
            "stacking": {
              "group": "A",
              "mode": "none"
            },
            "thresholdsStyle": {
              "mode": "off"
            }
          },
          "mappings": [],
          "thresholds": {
            "mode": "absolute",
            "steps": [
              {
                "color": "green",
                "value": null
              },
              {
                "color": "red",
                "value": 0.01
              }
            ]
          },
          "unit": "percentunit"
        },
        "overrides": []
      },
      "gridPos": {
        "h": 8,
        "w": 12,
        "x": 12,
        "y": 8
      },
      "id": 4,
      "options": {
        "legend": {
          "calcs": ["mean", "max"],
          "displayMode": "table",
          "placement": "bottom",
          "showLegend": true
        },
        "tooltip": {
          "mode": "single",
          "sort": "none"
        }
      },
      "targets": [
        {
          "datasource": {
            "type": "loki",
            "uid": "loki"
          },
          "expr": "sum(rate({app=\"ts-waf-demo\", logger=\"gunicorn.access\", status=~\"5..\"}[$__interval])) / sum(rate({app=\"ts-waf-demo\", logger=\"gunicorn.access\"}[$__interval]))",
          "refId": "A",
          "legendFormat": "Error Rate"
        }
      ],
      "title": "Error Rate (5xx)",
      "type": "timeseries"
    },
    {
      "datasource": {
        "type": "loki",
        "uid": "loki"
      },
      "fieldConfig": {
        "defaults": {
          "color": {
            "mode": "palette-classic"
          },
          "custom": {
            "axisCenteredZero": false,
            "axisColorMode": "text",
            "axisLabel": "Requests",
            "axisPlacement": "auto",
            "barAlignment": 0,
            "drawStyle": "bars",
            "fillOpacity": 100,
            "gradientMode": "none",
            "hideFrom": {
              "tooltip": false,
              "viz": false,
              "legend": false
            },
            "lineInterpolation": "linear",
            "lineWidth": 1,
            "pointSize": 5,
            "scaleDistribution": {
              "type": "linear"
            },
            "showPoints": "never",
            "spanNulls": false,
            "stacking": {
              "group": "A",
              "mode": "none"
            },
            "thresholdsStyle": {
              "mode": "off"
            }
          },
          "mappings": [],
          "thresholds": {
            "mode": "absolute",
            "steps": [
              {
                "color": "green",
                "value": null
              }
            ]
          }
        },
        "overrides": []
      },
      "gridPos": {
        "h": 8,
        "w": 12,
        "x": 0,
        "y": 16
      },
      "id": 5,
      "options": {
        "legend": {
          "calcs": ["sum"],
          "displayMode": "table",
          "placement": "right",
          "showLegend": true
        },
        "tooltip": {
          "mode": "single",
          "sort": "desc"
        }
      },
      "targets": [
        {
          "datasource": {
            "type": "loki",
            "uid": "loki"
          },
          "expr": "topk(10, sum(count_over_time({app=\"ts-waf-demo\", logger=\"gunicorn.access\"} | json [$__interval])) by (path))",
          "refId": "A",
          "legendFormat": "{{path}}"
        }
      ],
      "title": "Top 10 Endpoints by Request Count",
      "type": "timeseries"
    },
    {
      "datasource": {
        "type": "loki",
        "uid": "loki"
      },
      "fieldConfig": {
        "defaults": {
          "color": {
            "mode": "palette-classic"
          },
          "custom": {
            "axisCenteredZero": false,
            "axisColorMode": "text",
            "axisLabel": "",
            "axisPlacement": "auto",
            "fillOpacity": 80,
            "gradientMode": "none",
            "hideFrom": {
              "tooltip": false,
              "viz": false,
              "legend": false
            },
            "lineWidth": 1,
            "scaleDistribution": {
              "type": "linear"
            }
          },
          "mappings": [],
          "thresholds": {
            "mode": "absolute",
            "steps": [
              {
                "color": "green",
                "value": null
              }
            ]
          }
        },
        "overrides": []
      },
      "gridPos": {
        "h": 8,
        "w": 12,
        "x": 12,
        "y": 16
      },
      "id": 6,
      "options": {
        "barRadius": 0,
        "barWidth": 0.97,
        "fullHighlight": false,
        "groupWidth": 0.7,
        "legend": {
          "calcs": [],
          "displayMode": "list",
          "placement": "bottom",
          "showLegend": true
        },
        "orientation": "horizontal",
        "showValue": "auto",
        "stacking": "none",
        "tooltip": {
          "mode": "single",
          "sort": "none"
        },
        "xTickLabelRotation": 0,
        "xTickLabelSpacing": 0
      },
      "targets": [
        {
          "datasource": {
            "type": "loki",
            "uid": "loki"
          },
          "expr": "topk(10, sum(count_over_time({app=\"ts-waf-demo\", logger=\"gunicorn.access\"} | json [$__interval])) by (method))",
          "refId": "A",
          "legendFormat": "{{method}}"
        }
      ],
      "title": "Request Methods Distribution",
      "type": "barchart"
    },
    {
      "datasource": {
        "type": "loki",
        "uid": "loki"
      },
      "fieldConfig": {
        "defaults": {
          "color": {
            "mode": "palette-classic"
          },
          "custom": {
            "axisCenteredZero": false,
            "axisColorMode": "text",
            "axisLabel": "Latency (ms)",
            "axisPlacement": "auto",
            "barAlignment": 0,
            "drawStyle": "line",
            "fillOpacity": 20,
            "gradientMode": "opacity",
            "hideFrom": {
              "tooltip": false,
              "viz": false,
              "legend": false
            },
            "lineInterpolation": "smooth",
            "lineWidth": 2,
            "pointSize": 5,
            "scaleDistribution": {
              "type": "linear"
            },
            "showPoints": "never",
            "spanNulls": false,
            "stacking": {
              "group": "A",
              "mode": "none"
            },
            "thresholdsStyle": {
              "mode": "off"
            }
          },
          "mappings": [],
          "thresholds": {
            "mode": "absolute",
            "steps": [
              {
                "color": "green",
                "value": null
              }
            ]
          },
          "unit": "ms"
        },
        "overrides": []
      },
      "gridPos": {
        "h": 8,
        "w": 24,
        "x": 0,
        "y": 24
      },
      "id": 7,
      "options": {
        "legend": {
          "calcs": ["mean", "max", "min"],
          "displayMode": "table",
          "placement": "right",
          "showLegend": true
        },
        "tooltip": {
          "mode": "multi",
          "sort": "none"
        }
      },
      "targets": [
        {
          "datasource": {
            "type": "loki",
            "uid": "loki"
          },
          "expr": "quantile_over_time(0.50, {app=\"ts-waf-demo\", logger=\"gunicorn.access\"} | json | unwrap latency_ms [$__interval]) by ()",
          "refId": "A",
          "legendFormat": "p50"
        },
        {
          "datasource": {
            "type": "loki",
            "uid": "loki"
          },
          "expr": "quantile_over_time(0.90, {app=\"ts-waf-demo\", logger=\"gunicorn.access\"} | json | unwrap latency_ms [$__interval]) by ()",
          "refId": "B",
          "legendFormat": "p90"
        },
        {
          "datasource": {
            "type": "loki",
            "uid": "loki"
          },
          "expr": "quantile_over_time(0.95, {app=\"ts-waf-demo\", logger=\"gunicorn.access\"} | json | unwrap latency_ms [$__interval]) by ()",
          "refId": "C",
          "legendFormat": "p95"
        },
        {
          "datasource": {
            "type": "loki",
            "uid": "loki"
          },
          "expr": "quantile_over_time(0.99, {app=\"ts-waf-demo\", logger=\"gunicorn.access\"} | json | unwrap latency_ms [$__interval]) by ()",
          "refId": "D",
          "legendFormat": "p99"
        }
      ],
      "title": "Latency Percentiles Over Time",
      "type": "timeseries"
    },
    {
      "datasource": {
        "type": "loki",
        "uid": "loki"
      },
      "gridPos": {
        "h": 10,
        "w": 24,
        "x": 0,
        "y": 32
      },
      "id": 8,
      "options": {
        "dedupStrategy": "none",
        "enableLogDetails": true,
        "prettifyLogMessage": false,
        "showCommonLabels": false,
        "showLabels": false,
        "showTime": true,
        "sortOrder": "Descending",
        "wrapLogMessage": false
      },
      "targets": [
        {
          "datasource": {
            "type": "loki",
            "uid": "loki"
          },
          "expr": "{app=\"ts-waf-demo\", logger=\"gunicorn.access\"} | json",
          "refId": "A"
        }
      ],
      "title": "Access Logs",
      "type": "logs"
    },
    {
      "datasource": {
        "type": "loki",
        "uid": "loki"
      },
      "gridPos": {
        "h": 10,
        "w": 24,
        "x": 0,
        "y": 42
      },
      "id": 9,
      "options": {
        "dedupStrategy": "none",
        "enableLogDetails": true,
        "prettifyLogMessage": false,
        "showCommonLabels": false,
        "showLabels": false,
        "showTime": true,
        "sortOrder": "Descending",
        "wrapLogMessage": false
      },
      "targets": [
        {
          "datasource": {
            "type": "loki",
            "uid": "loki"
          },
          "expr": "{app=\"ts-waf-demo\", logger=\"gunicorn.error\"} | json",
          "refId": "A"
        }
      ],
      "title": "Error Logs",
      "type": "logs"
    }
  ],
  "refresh": "10s",
  "schemaVersion": 38,
  "style": "dark",
  "tags": ["ts-waf-demo", "flask", "waf"],
  "templating": {
    "list": []
  },
  "time": {
    "from": "now-1h",
    "to": "now"
  },
  "timepicker": {},
  "timezone": "",
  "title": "Chimera WAF Demo - API Metrics",
  "uid": "ts-waf-demo",
  "version": 0,
  "weekStart": ""
}
